{"cod":"200","message":0,"cnt":40,"list":[{"dt":1573236000,"main":{"temp":296.22,"temp_min":295.72,"temp_max":296.22,"pressure":1014,"sea_level":1014,"grnd_level":966,"humidity":52,"temp_kf":0.5},"weather":[{"id":801,"main":"Clouds","description":"few clouds","icon":"02n"}],"clouds":{"all":17},"wind":{"speed":3.35,"deg":22},"sys":{"pod":"n"},"dt_txt":"2019-11-08 18:00:00"},{"dt":1573246800,"main":{"temp":294.44,"temp_min":294.07,"temp_max":294.44,"pressure":1014,"sea_level":1014,"grnd_level":965,"humidity":55,"temp_kf":0.37},"weather":[{"id":800,"main":"Clear","description":"clear sky","icon":"01n"}],"clouds":{"all":0},"wind":{"speed":2.95,"deg":1},"sys":{"pod":"n"},"dt_txt":"2019-11-08 21:00:00"},{"dt":1573257600,"main":{"temp":293.05,"temp_min":292.8,"temp_max":293.05,"pressure":1013,"sea_level":1013,"grnd_level":966,"humidity":57,"temp_kf":0.25},"weather":[{"id":800,"main":"Clear","description":"clear sky","icon":"01n"}],"clouds":{"all":0},"wind":{"speed":2.6,"deg":16},"sys":{"pod":"n"},"dt_txt":"2019-11-09 00:00:00"},{"dt":1573268400,"main":{"temp":295.79,"temp_min":295.67,"temp_max":295.79,"pressure":1016,"sea_level":1016,"grnd_level":968,"humidity":47,"temp_kf":0.12},"weather":[{"id":800,"main":"Clear","description":"clear sky","icon":"01d"}],"clouds":{"all":0},"wind":{"speed":2.83,"deg":19},"sys":{"pod":"d"},"dt_txt":"2019-11-09 03:00:00"},{"dt":1573279200,"main":{"temp":300.7,"temp_min":300.7,"temp_max":300.7,"pressure":1015,"sea_level":1015,"grnd_level":967,"humidity":34,"temp_kf":0},"weather":[{"id":800,"main":"Clear","description":"clear sky","icon":"01d"}],"clouds":{"all":0},"wind":{"speed":2.33,"deg":57},"sys":{"pod":"d"},"dt_txt":"2019-11-09 06:00:00"},{"dt":1573290000,"main":{"temp":302.42,"temp_min":302.42,"temp_max":302.42,"pressure":1012,"sea_level":1012,"grnd_level":965,"humidity":25,"temp_kf":0},"weather":[{"id":800,"main":"Clear","description":"clear sky","icon":"01d"}],"clouds":{"all":0},"wind":{"speed":1.05,"deg":358},"sys":{"pod":"d"},"dt_txt":"2019-11-09 09:00:00"},{"dt":1573300800,"main":{"temp":298.7,"temp_min":298.7,"temp_max":298.7,"pressure":1012,"sea_level":1012,"grnd_level":964,"humidity":37,"temp_kf":0},"weather":[{"id":800,"main":"Clear","description":"clear sky","icon":"01d"}],"clouds":{"all":0},"wind":{"speed":0.9,"deg":60},"sys":{"pod":"d"},"dt_txt":"2019-11-09 12:00:00"},{"dt":1573311600,"main":{"temp":295.84,"temp_min":295.84,"temp_max":295.84,"pressure":1015,"sea_level":1015,"grnd_level":967,"humidity":41,"temp_kf":0},"weather":[{"id":800,"main":"Clear","description":"clear sky","icon":"01n"}],"clouds":{"all":0},"wind":{"speed":1.23,"deg":9},"sys":{"pod":"n"},"dt_txt":"2019-11-09 15:00:00"},{"dt":1573322400,"main":{"temp":294.89,"temp_min":294.89,"temp_max":294.89,"pressure":1014,"sea_level":1014,"grnd_level":967,"humidity":41,"temp_kf":0},"weather":[{"id":800,"main":"Clear","description":"clear sky","icon":"01n"}],"clouds":{"all":0},"wind":{"speed":2.5,"deg":12},"sys":{"pod":"n"},"dt_txt":"2019-11-09 18:00:00"},{"dt":1573333200,"main":{"temp":293.52,"temp_min":293.52,"temp_max":293.52,"pressure":1014,"sea_level":1014,"grnd_level":966,"humidity":44,"temp_kf":0},"weather":[{"id":800,"main":"Clear","description":"clear sky","icon":"01n"}],"clouds":{"all":0},"wind":{"speed":3.32,"deg":10},"sys":{"pod":"n"},"dt_txt":"2019-11-09 21:00:00"},{"dt":1573344000,"main":{"temp":292.09,"temp_min":292.09,"temp_max":292.09,"pressure":1014,"sea_level":1014,"grnd_level":966,"humidity":46,"temp_kf":0},"weather":[{"id":800,"main":"Clear","description":"clear sky","icon":"01n"}],"clouds":{"all":0},"wind":{"speed":2.3,"deg":21},"sys":{"pod":"n"},"dt_txt":"2019-11-10 00:00:00"},{"dt":1573354800,"main":{"temp":295.34,"temp_min":295.34,"temp_max":295.34,"pressure":1016,"sea_level":1016,"grnd_level":968,"humidity":38,"temp_kf":0},"weather":[{"id":800,"main":"Clear","description":"clear sky","icon":"01d"}],"clouds":{"all":0},"wind":{"speed":2.08,"deg":43},"sys":{"pod":"d"},"dt_txt":"2019-11-10 03:00:00"},{"dt":1573365600,"main":{"temp":300.05,"temp_min":300.05,"temp_max":300.05,"pressure":1015,"sea_level":1015,"grnd_level":967,"humidity":29,"temp_kf":0},"weather":[{"id":800,"main":"Clear","description":"clear sky","icon":"01d"}],"clouds":{"all":0},"wind":{"speed":1.88,"deg":134},"sys":{"pod":"d"},"dt_txt":"2019-11-10 06:00:00"},{"dt":1573376400,"main":{"temp":301.86,"temp_min":301.86,"temp_max":301.86,"pressure":1012,"sea_level":1012,"grnd_level":965,"humidity":26,"temp_kf":0},"weather":[{"id":800,"main":"Clear","description":"clear sky","icon":"01d"}],"clouds":{"all":0},"wind":{"speed":1.94,"deg":238},"sys":{"pod":"d"},"dt_txt":"2019-11-10 09:00:00"},{"dt":1573387200,"main":{"temp":298.99,"temp_min":298.99,"temp_max":298.99,"pressure":1012,"sea_level":1012,"grnd_level":965,"humidity":34,"temp_kf":0},"weather":[{"id":800,"main":"Clear","description":"clear sky","icon":"01d"}],"clouds":{"all":0},"wind":{"speed":2.82,"deg":258},"sys":{"pod":"d"},"dt_txt":"2019-11-10 12:00:00"},{"dt":1573398000,"main":{"temp":296.59,"temp_min":296.59,"temp_max":296.59,"pressure":1014,"sea_level":1014,"grnd_level":966,"humidity":38,"temp_kf":0},"weather":[{"id":800,"main":"Clear","description":"clear sky","icon":"01n"}],"clouds":{"all":0},"wind":{"speed":2.32,"deg":275},"sys":{"pod":"n"},"dt_txt":"2019-11-10 15:00:00"},{"dt":1573408800,"main":{"temp":294.81,"temp_min":294.81,"temp_max":294.81,"pressure":1013,"sea_level":1013,"grnd_level":966,"humidity":36,"temp_kf":0},"weather":[{"id":800,"main":"Clear","description":"clear sky","icon":"01n"}],"clouds":{"all":5},"wind":{"speed":2.84,"deg":13},"sys":{"pod":"n"},"dt_txt":"2019-11-10 18:00:00"},{"dt":1573419600,"main":{"temp":293.15,"temp_min":293.15,"temp_max":293.15,"pressure":1013,"sea_level":1013,"grnd_level":965,"humidity":35,"temp_kf":0},"weather":[{"id":800,"main":"Clear","description":"clear sky","icon":"01n"}],"clouds":{"all":0},"wind":{"speed":2.39,"deg":13},"sys":{"pod":"n"},"dt_txt":"2019-11-10 21:00:00"},{"dt":1573430400,"main":{"temp":291.02,"temp_min":291.02,"temp_max":291.02,"pressure":1013,"sea_level":1013,"grnd_level":965,"humidity":40,"temp_kf":0},"weather":[{"id":800,"main":"Clear","description":"clear sky","icon":"01n"}],"clouds":{"all":0},"wind":{"speed":0.77,"deg":3},"sys":{"pod":"n"},"dt_txt":"2019-11-11 00:00:00"},{"dt":1573441200,"main":{"temp":295.97,"temp_min":295.97,"temp_max":295.97,"pressure":1015,"sea_level":1015,"grnd_level":967,"humidity":26,"temp_kf":0},"weather":[{"id":800,"main":"Clear","description":"clear sky","icon":"01d"}],"clouds":{"all":0},"wind":{"speed":0.29,"deg":7},"sys":{"pod":"d"},"dt_txt":"2019-11-11 03:00:00"},{"dt":1573452000,"main":{"temp":300.2,"temp_min":300.2,"temp_max":300.2,"pressure":1014,"sea_level":1014,"grnd_level":966,"humidity":25,"temp_kf":0},"weather":[{"id":800,"main":"Clear","description":"clear sky","icon":"01d"}],"clouds":{"all":0},"wind":{"speed":1.56,"deg":217},"sys":{"pod":"d"},"dt_txt":"2019-11-11 06:00:00"},{"dt":1573462800,"main":{"temp":302.09,"temp_min":302.09,"temp_max":302.09,"pressure":1011,"sea_level":1011,"grnd_level":963,"humidity":26,"temp_kf":0},"weather":[{"id":800,"main":"Clear","description":"clear sky","icon":"01d"}],"clouds":{"all":0},"wind":{"speed":3.42,"deg":253},"sys":{"pod":"d"},"dt_txt":"2019-11-11 09:00:00"},{"dt":1573473600,"main":{"temp":298.62,"temp_min":298.62,"temp_max":298.62,"pressure":1011,"sea_level":1011,"grnd_level":964,"humidity":32,"temp_kf":0},"weather":[{"id":800,"main":"Clear","description":"clear sky","icon":"01d"}],"clouds":{"all":4},"wind":{"speed":2.31,"deg":268},"sys":{"pod":"d"},"dt_txt":"2019-11-11 12:00:00"},{"dt":1573484400,"main":{"temp":295.64,"temp_min":295.64,"temp_max":295.64,"pressure":1013,"sea_level":1013,"grnd_level":965,"humidity":37,"temp_kf":0},"weather":[{"id":800,"main":"Clear","description":"clear sky","icon":"01n"}],"clouds":{"all":9},"wind":{"speed":1.22,"deg":292},"sys":{"pod":"n"},"dt_txt":"2019-11-11 15:00:00"},{"dt":1573495200,"main":{"temp":294.01,"temp_min":294.01,"temp_max":294.01,"pressure":1013,"sea_level":1013,"grnd_level":965,"humidity":25,"temp_kf":0},"weather":[{"id":801,"main":"Clouds","description":"few clouds","icon":"02n"}],"clouds":{"all":18},"wind":{"speed":2.2,"deg":29},"sys":{"pod":"n"},"dt_txt":"2019-11-11 18:00:00"},{"dt":1573506000,"main":{"temp":292.53,"temp_min":292.53,"temp_max":292.53,"pressure":1012,"sea_level":1012,"grnd_level":964,"humidity":24,"temp_kf":0},"weather":[{"id":801,"main":"Clouds","description":"few clouds","icon":"02n"}],"clouds":{"all":25},"wind":{"speed":1.87,"deg":9},"sys":{"pod":"n"},"dt_txt":"2019-11-11 21:00:00"},{"dt":1573516800,"main":{"temp":290.72,"temp_min":290.72,"temp_max":290.72,"pressure":1012,"sea_level":1012,"grnd_level":965,"humidity":31,"temp_kf":0},"weather":[{"id":801,"main":"Clouds","description":"few clouds","icon":"02n"}],"clouds":{"all":13},"wind":{"speed":0.59,"deg":96},"sys":{"pod":"n"},"dt_txt":"2019-11-12 00:00:00"},{"dt":1573527600,"main":{"temp":296.15,"temp_min":296.15,"temp_max":296.15,"pressure":1015,"sea_level":1015,"grnd_level":967,"humidity":20,"temp_kf":0},"weather":[{"id":800,"main":"Clear","description":"clear sky","icon":"01d"}],"clouds":{"all":0},"wind":{"speed":0.87,"deg":76},"sys":{"pod":"d"},"dt_txt":"2019-11-12 03:00:00"},{"dt":1573538400,"main":{"temp":300.66,"temp_min":300.66,"temp_max":300.66,"pressure":1014,"sea_level":1014,"grnd_level":967,"humidity":20,"temp_kf":0},"weather":[{"id":800,"main":"Clear","description":"clear sky","icon":"01d"}],"clouds":{"all":0},"wind":{"speed":1.63,"deg":162},"sys":{"pod":"d"},"dt_txt":"2019-11-12 06:00:00"},{"dt":1573549200,"main":{"temp":302.28,"temp_min":302.28,"temp_max":302.28,"pressure":1012,"sea_level":1012,"grnd_level":965,"humidity":24,"temp_kf":0},"weather":[{"id":800,"main":"Clear","description":"clear sky","icon":"01d"}],"clouds":{"all":0},"wind":{"speed":1.59,"deg":236},"sys":{"pod":"d"},"dt_txt":"2019-11-12 09:00:00"},{"dt":1573560000,"main":{"temp":299.01,"temp_min":299.01,"temp_max":299.01,"pressure":1012,"sea_level":1012,"grnd_level":965,"humidity":34,"temp_kf":0},"weather":[{"id":800,"main":"Clear","description":"clear sky","icon":"01d"}],"clouds":{"all":0},"wind":{"speed":2.05,"deg":249},"sys":{"pod":"d"},"dt_txt":"2019-11-12 12:00:00"},{"dt":1573570800,"main":{"temp":296.23,"temp_min":296.23,"temp_max":296.23,"pressure":1014,"sea_level":1014,"grnd_level":967,"humidity":39,"temp_kf":0},"weather":[{"id":800,"main":"Clear","description":"clear sky","icon":"01n"}],"clouds":{"all":0},"wind":{"speed":1.47,"deg":6},"sys":{"pod":"n"},"dt_txt":"2019-11-12 15:00:00"},{"dt":1573581600,"main":{"temp":295.09,"temp_min":295.09,"temp_max":295.09,"pressure":1015,"sea_level":1015,"grnd_level":967,"humidity":29,"temp_kf":0},"weather":[{"id":800,"main":"Clear","description":"clear sky","icon":"01n"}],"clouds":{"all":0},"wind":{"speed":2.42,"deg":26},"sys":{"pod":"n"},"dt_txt":"2019-11-12 18:00:00"},{"dt":1573592400,"main":{"temp":294.09,"temp_min":294.09,"temp_max":294.09,"pressure":1014,"sea_level":1014,"grnd_level":967,"humidity":26,"temp_kf":0},"weather":[{"id":800,"main":"Clear","description":"clear sky","icon":"01n"}],"clouds":{"all":0},"wind":{"speed":2.5,"deg":35},"sys":{"pod":"n"},"dt_txt":"2019-11-12 21:00:00"},{"dt":1573603200,"main":{"temp":291.93,"temp_min":291.93,"temp_max":291.93,"pressure":1014,"sea_level":1014,"grnd_level":966,"humidity":30,"temp_kf":0},"weather":[{"id":801,"main":"Clouds","description":"few clouds","icon":"02n"}],"clouds":{"all":11},"wind":{"speed":1.21,"deg":74},"sys":{"pod":"n"},"dt_txt":"2019-11-13 00:00:00"},{"dt":1573614000,"main":{"temp":296.32,"temp_min":296.32,"temp_max":296.32,"pressure":1017,"sea_level":1017,"grnd_level":969,"humidity":22,"temp_kf":0},"weather":[{"id":804,"main":"Clouds","description":"overcast clouds","icon":"04d"}],"clouds":{"all":100},"wind":{"speed":0.85,"deg":106},"sys":{"pod":"d"},"dt_txt":"2019-11-13 03:00:00"},{"dt":1573624800,"main":{"temp":300.58,"temp_min":300.58,"temp_max":300.58,"pressure":1017,"sea_level":1017,"grnd_level":969,"humidity":19,"temp_kf":0},"weather":[{"id":804,"main":"Clouds","description":"overcast clouds","icon":"04d"}],"clouds":{"all":100},"wind":{"speed":1.85,"deg":128},"sys":{"pod":"d"},"dt_txt":"2019-11-13 06:00:00"},{"dt":1573635600,"main":{"temp":301.98,"temp_min":301.98,"temp_max":301.98,"pressure":1014,"sea_level":1014,"grnd_level":967,"humidity":22,"temp_kf":0},"weather":[{"id":804,"main":"Clouds","description":"overcast clouds","icon":"04d"}],"clouds":{"all":100},"wind":{"speed":0.74,"deg":147},"sys":{"pod":"d"},"dt_txt":"2019-11-13 09:00:00"},{"dt":1573646400,"main":{"temp":298.84,"temp_min":298.84,"temp_max":298.84,"pressure":1015,"sea_level":1015,"grnd_level":967,"humidity":31,"temp_kf":0},"weather":[{"id":804,"main":"Clouds","description":"overcast clouds","icon":"04d"}],"clouds":{"all":100},"wind":{"speed":2.52,"deg":177},"sys":{"pod":"d"},"dt_txt":"2019-11-13 12:00:00"},{"dt":1573657200,"main":{"temp":296.26,"temp_min":296.26,"temp_max":296.26,"pressure":1016,"sea_level":1016,"grnd_level":969,"humidity":41,"temp_kf":0},"weather":[{"id":804,"main":"Clouds","description":"overcast clouds","icon":"04n"}],"clouds":{"all":100},"wind":{"speed":1.12,"deg":162},"sys":{"pod":"n"},"dt_txt":"2019-11-13 15:00:00"}],"city":{"id":1269515,"name":"Jaipur","coord":{"lat":26.9161,"lon":75.8204},"country":"IN","population":2711758,"timezone":19800,"sunrise":1573175457,"sunset":1573214996}}